gitpull
gitpull.py
setup.py
gitpull.egg-info/PKG-INFO
gitpull.egg-info/SOURCES.txt
gitpull.egg-info/dependency_links.txt
gitpull.egg-info/requires.txt
gitpull.egg-info/top_level.txt