Metadata-Version: 1.0
Name: gitpull
Version: 0.2
Summary: A python script for batch-pull git repos
Home-page: https://github.com/adamatan/gitpull
Author: Adam Matan
Author-email: adam@matan.name
License: MIT
Platform: UNKNOWN
